kombu_sakura_simplemq/__init__.py
kombu_sakura_simplemq/transport.py
kombu_sakura_simplemq-0.2.0.dist-info/METADATA
kombu_sakura_simplemq-0.2.0.dist-info/WHEEL
kombu_sakura_simplemq-0.2.0.dist-info/licenses/LICENCE.txt
kombu_sakura_simplemq-0.2.0.dist-info/RECORD
