Metadata-Version: 2.4
Name: kombu-sakura-simplemq
Version: 0.2.0
Summary: Kombu Tramsport for Sakura Cloud SimpleMQ
Project-URL: Homepage, https://github.com/chibiegg/kombu-sakura-simplemq
Project-URL: Repository, https://github.com/chibiegg/kombu-sakura-simplemq
Project-URL: Issue Tracker, https://github.com/chibiegg/kombu-sakura-simplemq/issues
License: MIT License
License-File: LICENCE.txt
Classifier: Development Status :: 3 - Alpha
Classifier: Intended Audience :: Developers
Classifier: Programming Language :: Python :: 3
Classifier: Programming Language :: Python :: 3 :: Only
Classifier: Programming Language :: Python :: 3.8
Classifier: Programming Language :: Python :: 3.9
Classifier: Programming Language :: Python :: 3.10
Classifier: Programming Language :: Python :: 3.11
Classifier: Programming Language :: Python :: 3.12
Classifier: Topic :: Software Development :: Build Tools
Requires-Dist: kombu
Requires-Dist: requests
